nu_lpw_v/__init__.py
nu_lpw_v/cvdl.py
nu_lpw_v/daa.py
nu_lpw_v/daa_java.py
nu_lpw_v/daa_parth.py
nu_lpw_v/dav.py
nu_lpw_v/ml_parth.py
nu_lpw_v/nlc.py
nu_lpw_v-0.0.9.dist-info/METADATA
nu_lpw_v-0.0.9.dist-info/WHEEL
nu_lpw_v-0.0.9.dist-info/top_level.txt
nu_lpw_v-0.0.9.dist-info/RECORD
